MANIFEST.in
README.md
setup.py
addignore/__init__.py
addignore/__version__.py
addignore/cli.py
addignore/exceptions.py
addignore/help.py
addignore/models.py
addignore/status_codes.py
addignore/utils.py
addignore.egg-info/PKG-INFO
addignore.egg-info/SOURCES.txt
addignore.egg-info/dependency_links.txt
addignore.egg-info/entry_points.txt
addignore.egg-info/not-zip-safe
addignore.egg-info/requires.txt
addignore.egg-info/top_level.txt