Metadata-Version: 2.1
Name: addignore
Version: 1.2.7
Summary: AzatAI Work Automation Tool. Adds Github .gitignore files automatically to your project, save your time and energy ~~~ 
Home-page: https://github.com/AzatAI/addignore
Author: Yaakov Azat
Author-email: yaakovazat@gmail.com
License: MIT
Project-URL: Documentation, https://azat.ai
Project-URL: Source, https://github.com/AzatAI/addignore
Platform: UNKNOWN
Classifier: Development Status :: 5 - Production/Stable
Classifier: Intended Audience :: Developers
Classifier: Natural Language :: English
Classifier: Programming Language :: Python
Classifier: Programming Language :: Python :: 3
Classifier: Programming Language :: Python :: 3.5
Classifier: Programming Language :: Python :: 3.6
Classifier: Programming Language :: Python :: 3.7
Classifier: Programming Language :: Python :: 3.8
Classifier: Programming Language :: Python :: Implementation :: CPython
Classifier: Programming Language :: Python :: Implementation :: PyPy
Requires-Python: >=3.5
